[
  {
    "chunk_id": "hindi_doc_0_0_bedc79326f",
    "doc_id": "doc_0",
    "chunk_idx": 0,
    "text": "(9) कुकों का विहंगम स्थान (9) कुकों का विहंगम विहार (9) कुकों का विहंगम विहार (9) कुकों का विहंगम विहार (9) कुकों का विहंगम विहार (9) कुकों का विहंगम विहार (9) कुकों का विहंगम विहार (9) कुकों का विहंगम विहार (9) कुकों का विहंगम विहार (9) कुकों का विहंगम विहार (9) कुकों का विहंगम विहार (9) कुकों का विहंगम विहार (9) कुकों का विहंगम विहार (9) कुकों का विहंगम विहार (9) कुकों का विहंगम विहार (9) कुकों",
    "parallel_id": "doc_0_0_bedc79326f"
  },
  {
    "chunk_id": "hindi_doc_0_1_dd079cadb7",
    "doc_id": "doc_0",
    "chunk_idx": 1,
    "text": "विहार (9) कुकों का विहंगम विहार (9) कुकों का विहंगम विहार (9) कुकों का विहंगम विहार (9) कुकों का विहंगम विहार (9) कुकों का विहंगम",
    "parallel_id": "doc_0_1_dd079cadb7"
  },
  {
    "chunk_id": "hindi_doc_0_2_de6069842a",
    "doc_id": "doc_0",
    "chunk_idx": 2,
    "text": "कोई भी विश्वसनीय सबूत साक्ष्य प्रस्तुत नहीं कर सकता है। अगर कुक बाबा बालाक सिंह या बाबा राम सिंह को उनकी व्यक्तिगत इच्छाओं के आधार पर केवल नामधारी संप्रदाय के रणनीतिक नेताओं के रूप में पेश करते हैं, तो उन्हें प्राचीन सिख इतिहास को विकृत करने की आवश्यकता नहीं होगी",
    "parallel_id": "doc_0_2_de6069842a"
  },
  {
    "chunk_id": "hindi_doc_0_3_73993674bc",
    "doc_id": "doc_0",
    "chunk_idx": 3,
    "text": "इस पुस्तक के लेखन के समय प्राप्त अनुभव के आधार पर, मुझे यह कहने के लिए मजबूर किया जा रहा है कि अपने पूर्वजों को अपने मनगढ़ंत विचारों के अनुसार उच्च स्तर पर बताने के लिए, जो लेखक अपने स्वयं के काल्पनिक कहानियों को अपने जीवन के अंत में मिलाते हैं, उतना ही अन्याय जो ये लेखक उन पूर्वजों के साथ करते हैं, शायद उनके कट्टर विरोधी भी नहीं कर सकते हैं",
    "parallel_id": "doc_0_3_73993674bc"
  },
  {
    "chunk_id": "hindi_doc_0_4_4bc9e41a64",
    "doc_id": "doc_0",
    "chunk_idx": 4,
    "text": "। कुछ समय के साथ वास्तविकता और भ्रांति की निंदा करना मुश्किल हो जाता है जिसका परिणाम यह होता है कि उथल-पुथल से चिंतित विचारशील पाठक कई सही वाक्यांशों को भी संदेह के साथ देखते हुए अस्वीकार कर देते हैं, इसलिए इतिहास में मनोवैज्ञानिक-काल्पनिक संलयनों के साथ लाभ और नुकसान हमेशा के लिए कायम रहता है, जिसे कभी भी पूरा नहीं किया जा सकता है।",
    "parallel_id": "doc_0_4_4bc9e41a64"
  },
  {
    "chunk_id": "hindi_doc_0_5_a64113411a",
    "doc_id": "doc_0",
    "chunk_idx": 5,
    "text": "दै सरदार भक्तों की नज़र में भविष्यवक्ताओं पर अपरिवर्तनीय अलौकिक चमत्कार महान लोगों की जीवनी का एक आवश्यक हिस्सा बन गए हैं, जिन्हें उनसे घर ले जाने के लिए भी अयोग्य नहीं माना जाता है, लेकिन वे यह समझते हैं कि इस तरह वे परेशान करने वाली आंखों के लिए किसी भी करीबी, भूतिया असाधारण, ऐतिहासिक वाक्यांश को भी संदिग्ध बना देते हैं",
    "parallel_id": "doc_0_5_a64113411a"
  },
  {
    "chunk_id": "hindi_doc_0_6_ba6f357600",
    "doc_id": "doc_0",
    "chunk_idx": 6,
    "text": "। यही हाल कोका संप्रदाय के नेता बाबा'बाल्क सिंह और बाबा राम सिंह के जीवन के साथ हो रहा है। इसलिए यह कहना मुश्किल हो रहा है कि उनके जीवन का कितना सच हो गया है, कितना आधा और कितना पांचवां।",
    "parallel_id": "doc_0_6_ba6f357600"
  }
]